openstates_metadata/__init__.py
openstates_metadata/_creation/create_data.sh
openstates_metadata/_creation/jurisdictions.csv
openstates_metadata/_creation/orgs.csv
openstates_metadata/_creation/settings.yml
openstates_metadata/_creation/write_data.py
openstates_metadata/data/__init__.py
openstates_metadata/data/ak.py
openstates_metadata/data/al.py
openstates_metadata/data/ar.py
openstates_metadata/data/asm.py
openstates_metadata/data/az.py
openstates_metadata/data/ca.py
openstates_metadata/data/co.py
openstates_metadata/data/ct.py
openstates_metadata/data/dc.py
openstates_metadata/data/de.py
openstates_metadata/data/fl.py
openstates_metadata/data/ga.py
openstates_metadata/data/gu.py
openstates_metadata/data/hi.py
openstates_metadata/data/ia.py
openstates_metadata/data/id.py
openstates_metadata/data/il.py
openstates_metadata/data/ind.py
openstates_metadata/data/ks.py
openstates_metadata/data/ky.py
openstates_metadata/data/la.py
openstates_metadata/data/legacy_districts.py
openstates_metadata/data/ma.py
openstates_metadata/data/md.py
openstates_metadata/data/me.py
openstates_metadata/data/mi.py
openstates_metadata/data/mn.py
openstates_metadata/data/mo.py
openstates_metadata/data/mp.py
openstates_metadata/data/ms.py
openstates_metadata/data/mt.py
openstates_metadata/data/nc.py
openstates_metadata/data/nd.py
openstates_metadata/data/ne.py
openstates_metadata/data/nh.py
openstates_metadata/data/nj.py
openstates_metadata/data/nm.py
openstates_metadata/data/nv.py
openstates_metadata/data/ny.py
openstates_metadata/data/oh.py
openstates_metadata/data/ok.py
openstates_metadata/data/ore.py
openstates_metadata/data/pa.py
openstates_metadata/data/pr.py
openstates_metadata/data/ri.py
openstates_metadata/data/sc.py
openstates_metadata/data/sd.py
openstates_metadata/data/states.py
openstates_metadata/data/tn.py
openstates_metadata/data/tx.py
openstates_metadata/data/us.py
openstates_metadata/data/ut.py
openstates_metadata/data/va.py
openstates_metadata/data/vi.py
openstates_metadata-2024.10.3.dist-info/METADATA
openstates_metadata-2024.10.3.dist-info/WHEEL
openstates_metadata-2024.10.3.dist-info/RECORD
