Metadata-Version: 2.1
Name: openstates_metadata
Version: 2024.10.3
Summary: Openstates metadata
License: MIT
Author: Alex Obaseki
Author-email: alex@pluralpolicy.com
Requires-Python: >=3.9,<4.0
Classifier: License :: OSI Approved :: MIT License
Classifier: Programming Language :: Python :: 3
Classifier: Programming Language :: Python :: 3.9
Classifier: Programming Language :: Python :: 3.10
Classifier: Programming Language :: Python :: 3.11
Classifier: Programming Language :: Python :: 3.12
Requires-Dist: attr (>=0.3.2,<0.4.0)
Requires-Dist: attrs (>=24.2.0,<25.0.0)
